{
    "N": {
        "apple": 40,
        "banana": 120,
        "blackgram": 60,
        "chickpea": 60,
        "coconut": 40,
        "coffee": 120,
        "cotton": 140,
        "grapes": 40,
        "jute": 100,
        "kidneybeans": 40,
        "lentil": 40,
        "maize": 100,
        "mango": 40,
        "mothbeans": 40,
        "mungbean": 40,
        "muskmelon": 120,
        "orange": 40,
        "papaya": 70,
        "pigeonpeas": 40,
        "pomegranate": 40,
        "rice": 99,
        "watermelon": 120
    },
    "P": {
        "apple": 145,
        "banana": 95,
        "blackgram": 80,
        "chickpea": 80,
        "coconut": 30,
        "coffee": 40,
        "cotton": 60,
        "grapes": 145,
        "jute": 60,
        "kidneybeans": 80,
        "lentil": 80,
        "maize": 60,
        "mango": 40,
        "mothbeans": 60,
        "mungbean": 60,
        "muskmelon": 30,
        "orange": 30,
        "papaya": 70,
        "pigeonpeas": 80,
        "pomegranate": 30,
        "rice": 60,
        "watermelon": 30
    },
    "K": {
        "apple": 205,
        "banana": 55,
        "blackgram": 25,
        "chickpea": 85,
        "coconut": 35,
        "coffee": 35,
        "cotton": 25,
        "grapes": 205,
        "jute": 45,
        "kidneybeans": 25,
        "lentil": 25,
        "maize": 25,
        "mango": 35,
        "mothbeans": 25,
        "mungbean": 25,
        "muskmelon": 55,
        "orange": 15,
        "papaya": 55,
        "pigeonpeas": 25,
        "pomegranate": 45,
        "rice": 45,
        "watermelon": 55
    }
}